fastapi_oidc_jwks/__init__.py
fastapi_oidc_jwks/dependency.py
fastapi_oidc_jwks/middleware.py
fastapi_oidc_jwks-0.1.1.dist-info/licenses/LICENSE
fastapi_oidc_jwks-0.1.1.dist-info/METADATA
fastapi_oidc_jwks-0.1.1.dist-info/WHEEL
fastapi_oidc_jwks-0.1.1.dist-info/top_level.txt
fastapi_oidc_jwks-0.1.1.dist-info/RECORD
